package/__init__.py
package/__main__.py
package/counting_sort.py
package/data_input.py
counting_sort-1.1.dist-info/METADATA
counting_sort-1.1.dist-info/WHEEL
counting_sort-1.1.dist-info/top_level.txt
counting_sort-1.1.dist-info/RECORD
