Metadata-Version: 2.1
Name: counting-sort
Version: 1.1
Summary: Пакет для сортировки чисел методом подсчета
Author: Мышенин Егор
Author-email: emyshenin@gmail.com
Classifier: Programming Language :: Python :: 3
Classifier: License :: OSI Approved :: MIT License
Classifier: Operating System :: OS Independent
Requires-Python: >=3.9
